pysesh/__init__.py
pysesh/env.py
pysesh/main.py
pysesh/session.py
pysesh-0.2.0.dist-info/METADATA
pysesh-0.2.0.dist-info/WHEEL
pysesh-0.2.0.dist-info/entry_points.txt
pysesh-0.2.0.dist-info/top_level.txt
pysesh-0.2.0.dist-info/RECORD
